flump/__init__.py
flump/error_handlers.py
flump/exceptions.py
flump/fetcher.py
flump/orm.py
flump/pagination.py
flump/schemas.py
flump/validators.py
flump/view.py
flump/web_utils.py
flump/methods/__init__.py
flump/methods/defs.py
flump/methods/delete.py
flump/methods/get_many.py
flump/methods/get_single.py
flump/methods/patch.py
flump/methods/post.py
flump-0.11.2.dist-info/DESCRIPTION.rst
flump-0.11.2.dist-info/METADATA
flump-0.11.2.dist-info/RECORD
flump-0.11.2.dist-info/WHEEL
flump-0.11.2.dist-info/metadata.json
flump-0.11.2.dist-info/top_level.txt
test/methods/__init__.py
test/methods/test_delete.py
test/methods/test_get_many.py
test/methods/test_get_single.py
test/methods/test_patch.py
test/methods/test_post.py
