Metadata-Version: 2.0
Name: flump
Version: 0.11.2
Summary: REST API builder using Flask routing and Marshmallow schemas.
Home-page: https://github.com/rolepoint/flump
Author: Carl Henderson
Author-email: carl@rolepoint.com
License: UNKNOWN
Download-URL: https://github.com/rolepoint/flump/archive/v0.11.2.tar.gz
Keywords: jsonapi marshmallow api schemas endpoints json rest web http flask python3 python2
Platform: UNKNOWN
Classifier: Development Status :: 4 - Beta
Classifier: Framework :: Flask
Classifier: Intended Audience :: Developers
Classifier: License :: OSI Approved :: MIT License
Classifier: Programming Language :: Python :: 2.7
Classifier: Programming Language :: Python :: 3.4
Classifier: Programming Language :: Python :: 3.5
Classifier: Topic :: Internet :: WWW/HTTP
Requires-Dist: marshmallow
Requires-Dist: flask
